LICENSE.txt
MANIFEST.in
README.rst
setup.cfg
setup.py
wiper/__init__.py
wiper/version.py
wiper/wiper.py
wiper.egg-info/PKG-INFO
wiper.egg-info/SOURCES.txt
wiper.egg-info/dependency_links.txt
wiper.egg-info/entry_points.txt
wiper.egg-info/not-zip-safe
wiper.egg-info/requires.txt
wiper.egg-info/top_level.txt