Metadata-Version: 1.1
Name: wiper
Version: 1.0.1
Summary: Wipe the APIC config and reprovision APICs.
Home-page: https://github.com/datacenter/wiper
Author: Mike Timm
Author-email: mtimm@cisco.com
License: UNKNOWN
Download-URL: https://github.com/datacenter/wiper/releases/tag/v1.0.1
Platform: UNKNOWN
Classifier: Development Status :: 4 - Beta
Classifier: Intended Audience :: Developers
Classifier: Natural Language :: English
Classifier: License :: OSI Approved :: Apache Software License
Classifier: Programming Language :: Python
Classifier: Programming Language :: Python :: 2.7
